package resolve_3;

/**
 * @Author 远志 zhangsong@cskaoyan.onaliyun.com
 * @Date 2024-08-24 15:54
 * @Version 1.0
 *  解析字节码文件
 *  不同类型的属性、方法在class字节码文件中的表示
 *  byte    B
 *  char    C
 *  short   S
 *  int     I
 *  float   F
 *  long    J
 *  double  D
 *  void    V
 *  引用类型    Ljava/Lang/String;等
 *  数组       [I 一维int数组
 *            [Ljava/Lang/String; 一维String数组
 *            [[I 二维int数组
 *
 *  参考：https://www.cnblogs.com/RDaneelOlivaw/p/13529474.html
 *  magic 4字节
 *  minor version 2字节
 *  major version 2字节
 *  constant pool count 2字节
 *  constant pool 待定
 *  access flag 2字节
 *  this_class类名 2字节
 *  super_class父类 2字节
 *  interfaces_count 2字节
 *  interfaces[] 待定
 *  fields_count 2字节
 *  fields_info 待定
 *  methods_count方法数量 2字节
 *  methods_info 待定
 *  attributes_count 2字节
 *  attributes[] 待定
 *
 *  原始class数据，未标注
 *  cafe babe 0000 0034 0022 0a00 0600 1409
 * 0015 0016 0800 170a 0018 0019 0700 1a07
 * 001b 0100 063c 696e 6974 3e01 0003 2829
 * 5601 0004 436f 6465 0100 0f4c 696e 654e
 * 756d 6265 7254 6162 6c65 0100 124c 6f63
 * 616c 5661 7269 6162 6c65 5461 626c 6501
 * 0004 7468 6973 0100 144c 7265 736f 6c76
 * 652f 5265 736f 6c76 654a 564d 3b01 0004
 * 6d61 696e 0100 1628 5b4c 6a61 7661 2f6c
 * 616e 672f 5374 7269 6e67 3b29 5601 0004
 * 6172 6773 0100 135b 4c6a 6176 612f 6c61
 * 6e67 2f53 7472 696e 673b 0100 0a53 6f75
 * 7263 6546 696c 6501 000f 5265 736f 6c76
 * 654a 564d 2e6a 6176 610c 0007 0008 0700
 * 1c0c 001d 001e 0100 0b48 656c 6c6f 2057
 * 6f72 6c64 0700 1f0c 0020 0021 0100 1272
 * 6573 6f6c 7665 2f52 6573 6f6c 7665 4a56
 * 4d01 0010 6a61 7661 2f6c 616e 672f 4f62
 * 6a65 6374 0100 106a 6176 612f 6c61 6e67
 * 2f53 7973 7465 6d01 0003 6f75 7401 0015
 * 4c6a 6176 612f 696f 2f50 7269 6e74 5374
 * 7265 616d 3b01 0013 6a61 7661 2f69 6f2f
 * 5072 696e 7453 7472 6561 6d01 0007 7072
 * 696e 746c 6e01 0015 284c 6a61 7661 2f6c
 * 616e 672f 5374 7269 6e67 3b29 5600 2100
 * 0500 0600 0000 0000 0200 0100 0700 0800
 * 0100 0900 0000 2f00 0100 0100 0000 052a
 * b700 01b1 0000 0002 000a 0000 0006 0001
 * 0000 0016 000b 0000 000c 0001 0000 0005
 * 000c 000d 0000 0009 000e 000f 0001 0009
 * 0000 0037 0002 0001 0000 0009 b200 0212
 * 03b6 0004 b100 0000 0200 0a00 0000 0a00
 * 0200 0000 1900 0800 1a00 0b00 0000 0c00
 * 0100 0000 0900 1000 1100 0000 0100 1200
 * 0000 0200 13
 *
 *
 *  如下的简单打印hello world的类字节码                                    0a=10 CONSTANT_Methodref
 *  cafe babe(magic默认值) 0000(次版本号) 0034(主版本号) 0022(常量池大小34) 0a00 0600 14(第一个常量池 1 + 2 + 2)09
 * 0015 0016(第二个常量池 09 fieldsref) 0800 17(第三个常量池)0a 0018 0019(第四个常量池) 0700 1a(第五个常量池)07
 * 001b(第6个常量池) 0100 063c 696e 6974 3e(第7个常量池 01是utf8_info 0006向后取6个字节)01 0003 2829
 * 56(第8个常量池)01 0004 436f 6465(第9个常量池) 0100 0f4c 696e 654e
 * 756d 6265 7254 6162 6c65(第10个常量池) 0100 124c 6f63
 * 616c 5661 7269 6162 6c65 5461 626c 65(第11个常量池)01
 * 0004 7468 6973(第12个常量池) 0100 144c 7265 736f 6c76
 * 652f 5265 736f 6c76 654a 564d 3b(第13个常量池)01 0004
 * 6d61 696e(第14个常量池) 0100 1628 5b4c 6a61 7661 2f6c
 * 616e 672f 5374 7269 6e67 3b29 56(第15个常量池)01 0004
 * 6172 6773(第16个常量池) 0100 135b 4c6a 6176 612f 6c61
 * 6e67 2f53 7472 696e 673b(第17个常量池) 0100 0a53 6f75
 * 7263 6546 696c 65(第18个常量池)01 000f 5265 736f 6c76
 * 654a 564d 2e6a 6176 61(第19个常量池)0c 0007 0008(第20个常量池 NameAndTypeInfo) 0700
 * 1c(第21个常量池 Class_info)0c 001d 001e(第22个常量池) 0100 0b48 656c 6c6f 2057
 * 6f72 6c64(第23个常量池) 0700 1f(第24个常量池)0c 0020 0021(第25个常量池) 0100 1272
 * 6573 6f6c 7665 2f52 6573 6f6c 7665 4a56
 * 4d(第26个常量池)01 0010 6a61 7661 2f6c 616e 672f 4f62
 * 6a65 6374(第27个常量池) 0100 106a 6176 612f 6c61 6e67
 * 2f53 7973 7465 6d(第28个常量池)01 0003 6f75 74(第29个常量池)01 0015
 * 4c6a 6176 612f 696f 2f50 7269 6e74 5374
 * 7265 616d 3b(第30个常量池)01 0013 6a61 7661 2f69 6f2f
 * 5072 696e 7453 7472 6561 6d(第31个常量池)01 0007 7072
 * 696e 746c 6e(第32个常量池)01 0015 284c 6a61 7661 2f6c
 * 616e 672f 5374 7269 6e67 3b29 56(第33个常量池)00 21(0x0021,是0x0020和0x0001的并集,即这是一个Public的类)00
 * 05(this_class第5号常量池)00 06(super_class第6号常量池)00 00(接口数量,为0所以后续不会出现接口的信息)00 00(fields_count属性数量)00 02(方法数量2,构造函数、main方法)00 01(第一个方法访问修饰符public)00 07(指向7号常量池)00 08(指向8号常量池)00
 * 01(att_count)00 09(指向9号常量池 Code)00 0000 2f(2f=47, 从attribute_length开始到该属性结尾总共47个字节)00 01(操作数栈大小)00 01(局部表大小)00 0000 05(code_length)2a
 * b700 01b1(方法体（字节码指令）) 0000(exception_table_length) 0002( attributes_count) 000a(常量池10号) 0000 0006 0001
 * 0000 0016 000b 0000 000c 0001 0000 0005
 * 000c 000d 0000 0009 000e 000f 0001 0009
 * 0000 0037 0002 0001 0000 0009 b200 0212
 * 03b6 0004 b100 0000 0200 0a00 0000 0a00
 * 0200 0000 1900 0800 1a00 0b00 0000 0c00
 * 0100 0000 0900 1000 1100 0000 0100 1200
 * 0000 0200 13
 */
public class ResolveJVM {

    public static void main(String[] args) {
        System.out.println("Hello World  ");
    }
}
